streetlevel/__init__.py
streetlevel/dataclasses.py
streetlevel/exif.py
streetlevel/geo.py
streetlevel/util.py
streetlevel/baidu/__init__.py
streetlevel/baidu/api.py
streetlevel/baidu/baidu.py
streetlevel/baidu/panorama.py
streetlevel/baidu/parse.py
streetlevel/baidu/util.py
streetlevel/ja/__init__.py
streetlevel/ja/api.py
streetlevel/ja/ja.py
streetlevel/ja/panorama.py
streetlevel/ja/parse.py
streetlevel/ja/util.py
streetlevel/kakao/__init__.py
streetlevel/kakao/api.py
streetlevel/kakao/kakao.py
streetlevel/kakao/panorama.py
streetlevel/kakao/parse.py
streetlevel/kakao/util.py
streetlevel/lookaround/__init__.py
streetlevel/lookaround/api.py
streetlevel/lookaround/auth.py
streetlevel/lookaround/geo.py
streetlevel/lookaround/lookaround.py
streetlevel/lookaround/panorama.py
streetlevel/lookaround/parse.py
streetlevel/lookaround/reproject.py
streetlevel/lookaround/util.py
streetlevel/lookaround/proto/GroundMetadataTile.proto
streetlevel/lookaround/proto/GroundMetadataTile_pb2.py
streetlevel/lookaround/proto/MuninViewState.proto
streetlevel/lookaround/proto/MuninViewState_pb2.py
streetlevel/lookaround/proto/__init__.py
streetlevel/lookaround/proto/generate.bat
streetlevel/mapy/__init__.py
streetlevel/mapy/api.py
streetlevel/mapy/mapy.py
streetlevel/mapy/panorama.py
streetlevel/mapy/parse.py
streetlevel/mapy/util.py
streetlevel/naver/__init__.py
streetlevel/naver/api.py
streetlevel/naver/model.py
streetlevel/naver/naver.py
streetlevel/naver/panorama.py
streetlevel/naver/parse.py
streetlevel/naver/util.py
streetlevel/naver/proto/Model.proto
streetlevel/naver/proto/Model_pb2.py
streetlevel/naver/proto/__init__.py
streetlevel/naver/proto/generate.bat
streetlevel/streetside/__init__.py
streetlevel/streetside/api.py
streetlevel/streetside/panorama.py
streetlevel/streetside/parse.py
streetlevel/streetside/streetside.py
streetlevel/streetside/util.py
streetlevel/streetview/__init__.py
streetlevel/streetview/api.py
streetlevel/streetview/depth.py
streetlevel-0.12.4.dist-info/METADATA
streetlevel-0.12.4.dist-info/WHEEL
streetlevel-0.12.4.dist-info/licenses/LICENSE
streetlevel-0.12.4.dist-info/RECORD
