Metadata-Version: 2.4
Name: streetlevel
Version: 0.12.4
Summary: Download panoramas and metadata from Street View, Look Around, and more
Project-URL: Homepage, https://github.com/sk-zk/streetlevel
Project-URL: Bug Tracker, https://github.com/sk-zk/streetlevel/issues
Author-email: sk-zk <sk-zk@users.noreply.github.com>
License-Expression: MIT
License-File: LICENSE
Classifier: Development Status :: 4 - Beta
Classifier: License :: OSI Approved :: MIT License
Classifier: Operating System :: OS Independent
Classifier: Programming Language :: Python :: 3
Classifier: Topic :: Scientific/Engineering :: GIS
Requires-Python: >=3.8
Requires-Dist: aiohttp
Requires-Dist: bd09convertor
Requires-Dist: coordinatesconverter
Requires-Dist: cython
Requires-Dist: numpy
Requires-Dist: pillow
Requires-Dist: protobuf>4
Requires-Dist: pycryptodome
Requires-Dist: pyequilib
Requires-Dist: pyexiv2
Requires-Dist: pyfrpc
Requires-Dist: pyproj
Requires-Dist: pytest
Requires-Dist: pytest-asyncio
Requires-Dist: requests
Requires-Dist: scipy
